odk/__init__.py
odk/admin.py
odk/apps.py
odk/forms.py
odk/models.py
odk/storage.py
odk/urls.py
odk/utils.py
odk/views.py
odk/locale/__init__.py
odk/migrations/0001_initial.py
odk/migrations/__init__.py
odk/openrosa/__init__.py
odk/openrosa/utils_push.py
odk/openrosa/view_pull.py
odk/openrosa/view_push.py
odk/templatetags/__init__.py
odk/templatetags/model_tags.py
odk/templatetags/settings_tags.py
odkdata/__init__.py
odkdata/admin.py
odkdata/apps.py
odkdata/create_model.py
odkdata/load_submit_data.py
odkdata/utils.py
odkdata/migrations/__init__.py
odkdata/models/__init__.py
django_odk-1.1.9.dist-info/LICENSE
django_odk-1.1.9.dist-info/METADATA
django_odk-1.1.9.dist-info/WHEEL
django_odk-1.1.9.dist-info/top_level.txt
django_odk-1.1.9.dist-info/RECORD
