Metadata-Version: 2.1
Name: django-odk
Version: 1.1.9
Summary: Django Data Collection tool using ODK Collect mobile App
Home-page: https://github.com/openHBP/django-odk
Author: Patrick HOUBEN
Author-email: p.houben@cra.wallonie.be
License: GPL-3.0-or-later
Platform: Linux
Classifier: Development Status :: 3 - Alpha
Classifier: Intended Audience :: Developers
Classifier: Topic :: Software Development
Classifier: Framework :: Django
Classifier: License :: OSI Approved :: GNU General Public License v3 or later (GPLv3+)
Classifier: Operating System :: POSIX :: Linux
Classifier: Programming Language :: Python :: 3.7
Classifier: Programming Language :: Python :: 3.8
Classifier: Programming Language :: Python :: 3.9
Classifier: Programming Language :: Python :: 3.10
License-File: LICENSE
Requires-Dist: django<10.0,>=3.2
Requires-Dist: django-braces<11.0,>=1.11
Requires-Dist: pyxform<11.0,>=1.10.0
Requires-Dist: xlsconv<11.0,>=1.3.0
Requires-Dist: pillow<20.0,>=9.1.1
Requires-Dist: lxml<20.0,>=4.9.0
